ljscode/__about__.py
ljscode/__init__.py
ljscode/plot.py
ljscode/utils.py
ljscode-0.0.3.dist-info/METADATA
ljscode-0.0.3.dist-info/WHEEL
ljscode-0.0.3.dist-info/licenses/LICENSE.txt
ljscode-0.0.3.dist-info/RECORD
